briefed_people_utils/__init__.py
briefed_people_utils/briefed_people_utils.py
briefed_people_utils-0.6.9.dist-info/LICENSE
briefed_people_utils-0.6.9.dist-info/METADATA
briefed_people_utils-0.6.9.dist-info/WHEEL
briefed_people_utils-0.6.9.dist-info/top_level.txt
briefed_people_utils-0.6.9.dist-info/RECORD
