Metadata-Version: 2.1
Name: briefed-people-utils
Version: 0.6.9
Summary: Tools to support collect and send publically available data to Briefed.
Home-page: https://Briefed.eu
Author: Marek Zaremba-Pike
Author-email: marekzp@gmail.com
License: MIT
Platform: UNKNOWN
Classifier: Programming Language :: Python :: 3
Classifier: License :: OSI Approved :: MIT License
Classifier: Operating System :: OS Independent
Requires-Dist: requests
Requires-Dist: bs4
Requires-Dist: lxml
